lino_presto/__init__.py
lino_presto/manage.py
lino_presto/lib/__init__.py
lino_presto/lib/accounting/__init__.py
lino_presto/lib/accounting/models.py
lino_presto/lib/accounting/fixtures/__init__.py
lino_presto/lib/accounting/fixtures/demo.py
lino_presto/lib/accounting/fixtures/demo_bookings.py
lino_presto/lib/accounting/fixtures/minimal_ledger.py
lino_presto/lib/accounting/fixtures/std.py
lino_presto/lib/accounting/management/commands/reregister.py
lino_presto/lib/cal/__init__.py
lino_presto/lib/cal/models.py
lino_presto/lib/cal/config/cal/Room/roster.weasy.html
lino_presto/lib/cal/fixtures/__init__.py
lino_presto/lib/cal/fixtures/demo2.py
lino_presto/lib/cal/fixtures/std.py
lino_presto/lib/contacts/__init__.py
lino_presto/lib/contacts/models.py
lino_presto/lib/contacts/config/contacts/Worker/roster.weasy.html
lino_presto/lib/contacts/fixtures/__init__.py
lino_presto/lib/contacts/fixtures/demo.py
lino_presto/lib/contacts/fixtures/std.py
lino_presto/lib/orders/__init__.py
lino_presto/lib/orders/models.py
lino_presto/lib/presto/__init__.py
lino_presto/lib/presto/help_texts.py
lino_presto/lib/presto/layouts.py
lino_presto/lib/presto/models.py
lino_presto/lib/presto/settings.py
lino_presto/lib/presto/user_types.py
lino_presto/lib/presto/workflows.py
lino_presto/lib/presto/config/contacts/Worker/week_planner.weasy.html
lino_presto/lib/presto/config/orders/Order/estimate.weasy.html
lino_presto/lib/presto/config/orders/Order/sheet.weasy.html
lino_presto/lib/presto/config/trading/VatProductInvoice/service_report.weasy.html
lino_presto/lib/presto/fixtures/__init__.py
lino_presto/lib/presto/fixtures/demo.py
lino_presto/lib/presto/fixtures/std.py
lino_presto/lib/presto/locale/django.pot
lino_presto/lib/presto/locale/de/LC_MESSAGES/django.mo
lino_presto/lib/presto/locale/de/LC_MESSAGES/django.po
lino_presto/lib/presto/locale/fr/LC_MESSAGES/django.po
lino_presto/lib/products/__init__.py
lino_presto/lib/products/models.py
lino_presto/lib/trading/__init__.py
lino_presto-25.4.0.dist-info/METADATA
lino_presto-25.4.0.dist-info/WHEEL
lino_presto-25.4.0.dist-info/licenses/COPYING
lino_presto-25.4.0.dist-info/licenses/LICENSE
lino_presto-25.4.0.dist-info/RECORD
